meta_automl/__init__.py
meta_automl/data_preparation/__init__.py
meta_automl/data_preparation/datasets_train_test_split.py
meta_automl/data_preparation/model.py
meta_automl/data_preparation/dataset/__init__.py
meta_automl/data_preparation/dataset/custom_dataset.py
meta_automl/data_preparation/dataset/dataset_base.py
meta_automl/data_preparation/dataset/openml_dataset.py
meta_automl/data_preparation/datasets_loaders/__init__.py
meta_automl/data_preparation/datasets_loaders/datasets_loader.py
meta_automl/data_preparation/datasets_loaders/openml_datasets_loader.py
meta_automl/data_preparation/file_system/__init__.py
meta_automl/data_preparation/file_system/cache.py
meta_automl/data_preparation/file_system/cache_properties.py
meta_automl/data_preparation/file_system/file_system.py
meta_automl/data_preparation/meta_features_extractors/__init__.py
meta_automl/data_preparation/meta_features_extractors/meta_features_extractor.py
meta_automl/data_preparation/meta_features_extractors/pymfe_extractor.py
meta_automl/data_preparation/models_loaders/__init__.py
meta_automl/data_preparation/models_loaders/fedot_pipelines_loader.py
meta_automl/data_preparation/models_loaders/knowledge_base_models_loader.py
meta_automl/data_preparation/models_loaders/models_loader.py
meta_automl/meta_algorithm/__init__.py
meta_automl/meta_algorithm/datasets_similarity_assessors/__init__.py
meta_automl/meta_algorithm/datasets_similarity_assessors/datasets_similarity_assessor.py
meta_automl/meta_algorithm/datasets_similarity_assessors/model_based_similarity_assessors.py
meta_automl/meta_algorithm/model_advisors/__init__.py
meta_automl/meta_algorithm/model_advisors/diverse_fedot_pipeline_advisor.py
meta_automl/meta_algorithm/model_advisors/model_advisor.py
MetaFEDOT-0.0.5.dist-info/LICENSE
MetaFEDOT-0.0.5.dist-info/METADATA
MetaFEDOT-0.0.5.dist-info/WHEEL
MetaFEDOT-0.0.5.dist-info/top_level.txt
MetaFEDOT-0.0.5.dist-info/RECORD
