Metadata-Version: 2.1
Name: MetaFEDOT
Version: 0.0.5
Summary: Framework for meta-optimisation in AutoML tasks
Author: NSS Lab
Author-email: itmo.nss.team@gmail.com
Project-URL: Homepage, https://github.com/ITMO-NSS-team/MetaFEDOT
Project-URL: Bug Tracker, https://github.com/ITMO-NSS-team/MetaFEDOT/issues
Classifier: Programming Language :: Python :: 3
Classifier: License :: OSI Approved :: BSD License
Classifier: Operating System :: OS Independent
License-File: LICENSE
Requires-Dist: fedot (==0.7.1)
Requires-Dist: numpy (==1.24.4)
Requires-Dist: openml (==0.14.0)
Requires-Dist: pandas (==2.0.3)
Requires-Dist: pymfe (==0.4.2)
Requires-Dist: pytest (==7.4.0)
Requires-Dist: scikit-learn (==1.3.0)
Requires-Dist: scipy (==1.10.1)
Requires-Dist: tqdm (==4.65.0)
Requires-Dist: thegolem (==0.3.1)
